{"is_source_file": true, "format": "JavaScript (React JSX)", "description": "This file defines a React functional component called NoteList that renders a list of note cards, each displaying note details and action buttons.", "external_files": [], "external_methods": ["React"], "published": ["NoteList"], "classes": [], "methods": [{"name": "NoteList({ notes, onSelect, onDelete })", "description": "React functional component that displays a list of notes with options to select or delete each note.", "scope": "", "scopeKind": ""}], "calls": ["React", "n.id", "onSelect(n.id)", "onDelete(n.id)", "new Date(n.updatedAt).toLocaleString()"], "search-terms": ["NoteList", "React component", "notes array", "onSelect", "onDelete", "note cards"], "state": 2, "file_id": 17, "knowledge_revision": 37, "git_revision": "", "ctags": [{"_type": "tag", "name": "NoteList", "path": "/home/kavia/workspace/code-generation/note-organizer-11826-11835/notes_app_frontend/src/components/NoteList.js", "pattern": "/^export default function NoteList({ notes, onSelect, onDelete }) {$/", "language": "JavaScript", "kind": "function", "signature": "({ notes, onSelect, onDelete })"}], "hash": "d515f9a895b9a7a24415c38bf6fd4993", "format-version": 4, "code-base-name": "notes_app_frontend", "filename": "notes_app_frontend/src/components/NoteList.js", "revision_history": [{"37": ""}]}